ska_sdp_wflow_low_selfcal/pipeline/distribute.py
ska_sdp_wflow_low_selfcal/pipeline/dp3_helper.py
ska_sdp_wflow_low_selfcal/pipeline/main.py
ska_sdp_wflow_low_selfcal/pipeline/operations.py
ska_sdp_wflow_low_selfcal/pipeline/support/H5parm_collector.py
ska_sdp_wflow_low_selfcal/pipeline/support/blank_image.py
ska_sdp_wflow_low_selfcal/pipeline/support/cluster.py
ska_sdp_wflow_low_selfcal/pipeline/support/combine_h5parms.py
ska_sdp_wflow_low_selfcal/pipeline/support/facet.py
ska_sdp_wflow_low_selfcal/pipeline/support/filter_skymodel.py
ska_sdp_wflow_low_selfcal/pipeline/support/make_region_file.py
ska_sdp_wflow_low_selfcal/pipeline/support/miscellaneous.py
ska_sdp_wflow_low_selfcal/pipeline/support/read_data.py
ska_sdp_wflow_low_selfcal/pipeline/support/skymodel_utils.py
ska_sdp_wflow_low_selfcal/pipeline/support/subtract_sector_models.py
ska_sdp_wflow_low_selfcal/pipeline/support/time.py
ska_sdp_wflow_low_selfcal/pipeline/version.py
ska_sdp_wflow_low_selfcal/pipeline/wsclean_helper.py
ska_sdp_wflow_low_selfcal-0.1.1.dist-info/LICENSE
ska_sdp_wflow_low_selfcal-0.1.1.dist-info/METADATA
ska_sdp_wflow_low_selfcal-0.1.1.dist-info/WHEEL
ska_sdp_wflow_low_selfcal-0.1.1.dist-info/entry_points.txt
ska_sdp_wflow_low_selfcal-0.1.1.dist-info/RECORD
