Metadata-Version: 2.1
Name: ska-sdp-wflow-low-selfcal
Version: 0.1.1
Summary: SKA LOW selfcal pipeline
License: "BSD-3-Clause"
Author: chiarasal
Author-email: chiara.salvoni@cgi.com
Requires-Python: >=3.9,<4.0
Classifier: License :: Other/Proprietary License
Classifier: Programming Language :: Python :: 3
Classifier: Programming Language :: Python :: 3.9
Classifier: Programming Language :: Python :: 3.10
Classifier: Programming Language :: Python :: 3.11
Classifier: Programming Language :: Python :: 3.12
Requires-Dist: astropy (>=5.2.2,<6.0.0)
Requires-Dist: bdsf (>=1.10.2,<2.0.0)
Requires-Dist: dask (>=2023.7.1,<2024.0.0)
Requires-Dist: dask-jobqueue (>=0.8.2,<0.9.0)
Requires-Dist: dask-mpi (>=2022.4.0,<2023.0.0)
Requires-Dist: glob2 (>=0.7,<0.8)
Requires-Dist: h5py (>=3.8.0,<4.0.0)
Requires-Dist: losoto (>=2.4.1,<3.0.0)
Requires-Dist: lsmtool (==1.4.11)
Requires-Dist: pathlib (>=1.0.1,<2.0.0)
Requires-Dist: pluggy (>=1.3.0,<2.0.0)
Requires-Dist: pytest (>=7.4.3,<8.0.0)
Requires-Dist: pytest-mock (>=3.12.0,<4.0.0)
Requires-Dist: python-casacore (>=3.5.2,<4.0.0)
Requires-Dist: requests (>=2.28.2,<3.0.0)
Requires-Dist: shapely (>=2.0.1,<3.0.0)
